{
    "id":  "ShellS",
    "framePaths":  [
                       "Content/Sprites/Weapons/Other/ShellS.images/image 0.png",
                       "Content/Sprites/Weapons/Other/ShellS.images/image 1.png",
                       "Content/Sprites/Weapons/Other/ShellS.images/image 2.png",
                       "Content/Sprites/Weapons/Other/ShellS.images/image 3.png",
                       "Content/Sprites/Weapons/Other/ShellS.images/image 4.png"
                   ],
    "originX":  5,
    "originY":  5,
    "mask":  {
                 "separate":  true,
                 "shape":  "PRECISE",
                 "boundsMode":  "AUTO",
                 "left":  null,
                 "top":  null,
                 "right":  null,
                 "bottom":  null
             }
}
